local_llm/CTTS.py
local_llm/LLM.py
local_llm/STT.py
local_llm/__init__.py
local_llm-0.1.1.dist-info/LICENSE
local_llm-0.1.1.dist-info/METADATA
local_llm-0.1.1.dist-info/WHEEL
local_llm-0.1.1.dist-info/top_level.txt
local_llm-0.1.1.dist-info/RECORD
