Metadata-Version: 2.1
Name: local-llm
Version: 0.1.1
Summary: Local-LLM is a llama.cpp server in Docker with OpenAI Style Endpoints.
Author: Josh XT
Author-email: josh@devxt.com
Requires-Python: >=3.10
License-File: LICENSE
Requires-Dist: fastapi
Requires-Dist: pydantic
Requires-Dist: requests
Requires-Dist: uvicorn
Requires-Dist: pyjwt
Requires-Dist: tiktoken
Requires-Dist: llama-cpp-python
Requires-Dist: python-dotenv
Requires-Dist: GPUtil
Requires-Dist: psutil
Requires-Dist: beautifulsoup4
Requires-Dist: whisper-cpp-pybind
Requires-Dist: pydub
Requires-Dist: ffmpeg
Requires-Dist: numpy >=1.22.0
Requires-Dist: soundfile >=0.12.1
Requires-Dist: transformers ==4.36.2
Requires-Dist: TTS >=0.21.3
Requires-Dist: requests >=2.31.0
Requires-Dist: tqdm >=4.66.1
Requires-Dist: importlib-metadata >=4.8.1
Requires-Dist: packaging >=23.2
Requires-Dist: pydantic >=1.10.13
Requires-Dist: sounddevice >=0.4.6
Requires-Dist: python-multipart >=0.0.6
Requires-Dist: cutlet >=0.3.0
Requires-Dist: unidic-lite >=1.0.8
Requires-Dist: torch >=2.1.0
Requires-Dist: torchaudio >=2.1.0
